mirrorbench/__init__.py
mirrorbench/cli.py
mirrorbench/adapters/__init__.py
mirrorbench/adapters/llm.py
mirrorbench/adapters/registry.py
mirrorbench/cache/__init__.py
mirrorbench/cache/keys.py
mirrorbench/cache/manager.py
mirrorbench/cache/sqlite_backend.py
mirrorbench/core/config.py
mirrorbench/core/constants.py
mirrorbench/core/env.py
mirrorbench/core/logging.py
mirrorbench/core/manifest.py
mirrorbench/core/plan.py
mirrorbench/core/runner.py
mirrorbench/core/telemetry.py
mirrorbench/core/executor/__init__.py
mirrorbench/core/executor/async_backend.py
mirrorbench/core/executor/backend_registry.py
mirrorbench/core/executor/controller.py
mirrorbench/core/executor/ray_backend.py
mirrorbench/core/executor/sync_backend.py
mirrorbench/core/models/__init__.py
mirrorbench/core/models/cache.py
mirrorbench/core/models/episodes.py
mirrorbench/core/models/errors.py
mirrorbench/core/models/messages.py
mirrorbench/core/models/plan.py
mirrorbench/core/models/registry.py
mirrorbench/core/models/run.py
mirrorbench/core/registry/__init__.py
mirrorbench/core/registry/components.py
mirrorbench/core/registry/decorators.py
mirrorbench/core/registry/entries.py
mirrorbench/core/registry/filters.py
mirrorbench/core/registry/loader.py
mirrorbench/core/registry/service.py
mirrorbench/core/run_db/__init__.py
mirrorbench/core/run_db/base.py
mirrorbench/core/run_db/schema.py
mirrorbench/core/run_db/sqlite.py
mirrorbench/datasets/__init__.py
mirrorbench/datasets/artifacts.py
mirrorbench/datasets/base_dataset.py
mirrorbench/datasets/jsonl_chatbot_arena_mirror.py
mirrorbench/datasets/jsonl_clariq_mirror.py
mirrorbench/datasets/jsonl_mirror_base.py
mirrorbench/datasets/jsonl_oasst1_mirror.py
mirrorbench/datasets/jsonl_qulac_mirror.py
mirrorbench/datasets/registry.py
mirrorbench/datasets/loaders/__init__.py
mirrorbench/datasets/loaders/base.py
mirrorbench/datasets/loaders/huggingface.py
mirrorbench/datasets/loaders/jsonl.py
mirrorbench/engine/__init__.py
mirrorbench/eval/__init__.py
mirrorbench-0.0.1.dist-info/METADATA
mirrorbench-0.0.1.dist-info/WHEEL
mirrorbench-0.0.1.dist-info/entry_points.txt
mirrorbench-0.0.1.dist-info/licenses/LICENSE
mirrorbench-0.0.1.dist-info/RECORD
