Metadata-Version: 2.4
Name: mirrorbench
Version: 0.0.1
Summary: An automatic & extensible Framework to Evaluate User-Proxy Agents for Human-Likeness.
Author-email: Ashutosh Hathidara <ashutosh.hathidara@sap.com>, Sebastian Schreiber <sebastian.schreiber@sap.com>
License: Apache-2.0
License-File: LICENSE
Requires-Python: >=3.12
Requires-Dist: datasets>=4.1.1
Requires-Dist: langchain-openai>=0.1.0
Requires-Dist: nltk>=3.9.2
Requires-Dist: openai>=1.40
Requires-Dist: platformdirs>=4.0
Requires-Dist: pydantic>=2.5
Requires-Dist: python-dotenv>=1.0
Requires-Dist: pyyaml>=6.0
Requires-Dist: rich>=14.2.0
Requires-Dist: structlog>=24.1
Requires-Dist: tenacity>=8.2.3
Requires-Dist: tiktoken>=0.7.0
Provides-Extra: dev
Requires-Dist: black>=24.3; extra == 'dev'
Requires-Dist: ipykernel>=7.0.1; extra == 'dev'
Requires-Dist: matplotlib>=3.10.7; extra == 'dev'
Requires-Dist: mypy>=1.7; extra == 'dev'
Requires-Dist: nox>=2023.11; extra == 'dev'
Requires-Dist: opentelemetry-api>=1.37.0; extra == 'dev'
Requires-Dist: opentelemetry-exporter-otlp>=1.37.0; extra == 'dev'
Requires-Dist: opentelemetry-sdk>=1.37.0; extra == 'dev'
Requires-Dist: pre-commit>=3.6; extra == 'dev'
Requires-Dist: pytest-cov>=4.1; extra == 'dev'
Requires-Dist: pytest>=7.4; extra == 'dev'
Requires-Dist: ruff>=0.1.9; extra == 'dev'
Requires-Dist: seaborn>=0.13.2; extra == 'dev'
